json2pdf_converter/__init__.py
json2pdf_converter/convert.py
json2pdf_Converter-0.5.dist-info/LICENSE
json2pdf_Converter-0.5.dist-info/METADATA
json2pdf_Converter-0.5.dist-info/WHEEL
json2pdf_Converter-0.5.dist-info/top_level.txt
json2pdf_Converter-0.5.dist-info/RECORD
