Metadata-Version: 2.1
Name: json2pdf-Converter
Version: 0.5
Summary: A package to convert JSON to PDF.
Author: Jigyashu Nager
Classifier: Programming Language :: Python :: 3
Classifier: License :: OSI Approved :: MIT License
Classifier: Operating System :: OS Independent
Requires-Python: >=3.7
License-File: LICENSE
Requires-Dist: pandas
Requires-Dist: jinja2
Requires-Dist: PyPDF2
Requires-Dist: pdfkit
